_version.py
cloud_tasks/__init__.py
cloud_tasks/cli.py
cloud_tasks/py.typed
cloud_tasks/common/__init__.py
cloud_tasks/common/base.py
cloud_tasks/common/config.py
cloud_tasks/common/logging_config.py
cloud_tasks/instance_manager/__init__.py
cloud_tasks/instance_manager/aws.py
cloud_tasks/instance_manager/azure.py
cloud_tasks/instance_manager/gcp.py
cloud_tasks/instance_manager/instance_manager.py
cloud_tasks/instance_manager/orchestrator.py
cloud_tasks/queue_manager/__init__.py
cloud_tasks/queue_manager/aws.py
cloud_tasks/queue_manager/azure.py
cloud_tasks/queue_manager/gcp.py
cloud_tasks/queue_manager/queue_manager.py
cloud_tasks/worker/__init__.py
cloud_tasks/worker/worker.py
rms_cloud_tasks-0.1.1.dist-info/licenses/LICENSE
rms_cloud_tasks-0.1.1.dist-info/METADATA
rms_cloud_tasks-0.1.1.dist-info/WHEEL
rms_cloud_tasks-0.1.1.dist-info/entry_points.txt
rms_cloud_tasks-0.1.1.dist-info/top_level.txt
rms_cloud_tasks-0.1.1.dist-info/RECORD
