Metadata-Version: 2.4
Name: rms-cloud-tasks
Version: 0.1.1
Summary: A scalable, multi-cloud task processing system
Maintainer-email: "Robert S. French" <rfrench@seti.org>
License: Apache-2.0
Project-URL: Homepage, https://github.com/SETI/rms-cloud-tasks
Project-URL: Repository, https://github.com/SETI/rms-cloud-tasks
Project-URL: Source, https://github.com/SETI/rms-cloud-tasks
Project-URL: Issues, https://github.com/SETI/rms-cloud-tasks/issues
Keywords: AWS,GCP,Azure
Classifier: Development Status :: 3 - Alpha
Classifier: Natural Language :: English
Classifier: Intended Audience :: Developers
Classifier: Topic :: Software Development :: Libraries :: Python Modules
Classifier: Topic :: Utilities
Classifier: License :: OSI Approved :: Apache Software License
Classifier: Programming Language :: Python :: 3
Classifier: Programming Language :: Python :: 3.10
Classifier: Programming Language :: Python :: 3.11
Classifier: Programming Language :: Python :: 3.12
Classifier: Programming Language :: Python :: 3.13
Classifier: Operating System :: MacOS :: MacOS X
Classifier: Operating System :: POSIX :: Linux
Classifier: Operating System :: Microsoft :: Windows
Requires-Python: >=3.10
License-File: LICENSE
Requires-Dist: aiohttp
Requires-Dist: asyncio
Requires-Dist: click
Requires-Dist: json-stream
Requires-Dist: numpy
Requires-Dist: prettytable
Requires-Dist: pydantic
Requires-Dist: pyyaml
Requires-Dist: rms-filecache
Requires-Dist: shortuuid
Requires-Dist: tqdm
Requires-Dist: boto3
Requires-Dist: google-cloud-billing
Requires-Dist: google-cloud-compute
Requires-Dist: google-cloud-monitoring
Requires-Dist: google-cloud-pubsub
Requires-Dist: google-cloud-storage
Dynamic: license-file
